imod/__init__.py
imod/schemata.py
imod/testing.py
imod/common/__init__.py
imod/common/statusinfo.py
imod/common/interfaces/__init__.py
imod/common/interfaces/iagnosticpackage.py
imod/common/interfaces/idict.py
imod/common/interfaces/ilinedatapackage.py
imod/common/interfaces/imaskingsettings.py
imod/common/interfaces/imodel.py
imod/common/interfaces/ipackage.py
imod/common/interfaces/ipackagebase.py
imod/common/interfaces/ipackageserializer.py
imod/common/interfaces/ipointdatapackage.py
imod/common/interfaces/iregridpackage.py
imod/common/interfaces/isimulation.py
imod/common/serializer/__init__.py
imod/common/serializer/netcdfserializer.py
imod/common/serializer/zarrserializer.py
imod/common/utilities/clip.py
imod/common/utilities/dataclass_type.py
imod/common/utilities/grid.py
imod/common/utilities/layer.py
imod/common/utilities/line_data.py
imod/common/utilities/mask.py
imod/common/utilities/regrid.py
imod/common/utilities/schemata.py
imod/common/utilities/value_filters.py
imod/common/utilities/version.py
imod/couplers/__init__.py
imod/couplers/metamod/__init__.py
imod/couplers/metamod/metamod.py
imod/data/__init__.py
imod/data/registry.txt
imod/data/sample_data.py
imod/data/synthetic.py
imod/evaluate/__init__.py
imod/evaluate/boundaries.py
imod/evaluate/budget.py
imod/evaluate/constraints.py
imod/evaluate/head.py
imod/evaluate/streamfunction.py
imod/formats/__init__.py
imod/formats/idf.py
imod/formats/ipf.py
imod/formats/rasterio.py
imod/formats/array_io/__init__.py
imod/formats/array_io/reading.py
imod/formats/array_io/writing.py
imod/formats/gen/__init__.py
imod/formats/gen/gen.py
imod/formats/prj/__init__.py
imod/formats/prj/prj.py
imod/logging/__init__.py
imod/logging/_loggerholder.py
imod/logging/config.py
imod/logging/ilogger.py
imod/logging/logging_decorators.py
imod/logging/loglevel.py
imod/logging/logurulogger.py
imod/logging/nulllogger.py
imod/logging/pythonlogger.py
imod/mf6/__init__.py
imod/mf6/adv.py
imod/mf6/api_package.py
imod/mf6/ats.py
imod-1.0.0.post1.dist-info/METADATA
imod-1.0.0.post1.dist-info/WHEEL
imod-1.0.0.post1.dist-info/licenses/LICENSE
imod-1.0.0.post1.dist-info/RECORD
