Metadata-Version: 2.4
Name: imod
Version: 1.0.0.post1
Summary: Make massive MODFLOW models!
Project-URL: Homepage, https://github.com/Deltares/imod-python
Project-URL: Documentation, https://deltares.github.io/imod-python/
Project-URL: Repository, https://github.com/Deltares/imod-python.git
Project-URL: Bug Tracker, https://github.com/Deltares/imod-python/issues
Project-URL: Changelog, https://github.com/Deltares/imod-python/blob/master/docs/api/changelog.rst
Author-email: Deltares <imod.info@deltares.nl>
Maintainer-email: Deltares <imod.info@deltares.nl>
License: MIT License
License-File: LICENSE
Keywords: groundwater modeling,imod,modflow
Classifier: Development Status :: 4 - Beta
Classifier: Intended Audience :: Science/Research
Classifier: License :: OSI Approved :: MIT License
Classifier: Operating System :: OS Independent
Classifier: Programming Language :: Python
Classifier: Programming Language :: Python :: 3
Classifier: Programming Language :: Python :: 3.11
Classifier: Programming Language :: Python :: 3.12
Classifier: Programming Language :: Python :: 3.13
Classifier: Programming Language :: Python :: Implementation :: CPython
Classifier: Topic :: Scientific/Engineering
Classifier: Topic :: Scientific/Engineering :: Hydrology
Requires-Python: >=3.11
Requires-Dist: affine
Requires-Dist: cftime>=1
Requires-Dist: dask
Requires-Dist: filelock
Requires-Dist: jinja2
Requires-Dist: loguru
Requires-Dist: matplotlib
Requires-Dist: numba
Requires-Dist: numpy
Requires-Dist: pandas
Requires-Dist: plum-dispatch
Requires-Dist: pooch
Requires-Dist: pydantic
Requires-Dist: scipy
Requires-Dist: tomli-w
Requires-Dist: tomli>=1.1.0
Requires-Dist: toolz
Requires-Dist: tqdm
Requires-Dist: xarray>=2023.08.0
Requires-Dist: xugrid>=0.14.0
Provides-Extra: all
Requires-Dist: bottleneck; extra == 'all'
Requires-Dist: contextily>=1; extra == 'all'
Requires-Dist: cytoolz; extra == 'all'
Requires-Dist: geopandas; extra == 'all'
Requires-Dist: pyvista; extra == 'all'
Requires-Dist: rasterio>=1; extra == 'all'
Requires-Dist: rioxarray; extra == 'all'
Requires-Dist: shapely>=1.8; extra == 'all'
Requires-Dist: zarr; extra == 'all'
